Metadata-Version: 2.1
Name: diffupy
Version: 0.0.5
Summary: Compute diffusion scores over networks
Home-page: https://github.com/multipaths/DiffuPy
Author: Josep Marín-Llaó, Sergi Picart Armada, Daniel Domingo-Fernández
Author-email: josepmarinllao@gmail.com
Maintainer: Josep Marín-Llaó
Maintainer-email: josepmarinllao@gmail.com
License: Apache 2.0 License
Download-URL: https://github.com/multipaths/DiffuPy
Project-URL: Bug Tracker, https://github.com/multipaths/DiffuPy/issues
Project-URL: Source Code, https://github.com/multipaths/DiffuPy
Project-URL: Documentation, https://diffupy.readthedocs.io
Keywords: Heat Diffusion,Systems Biology,Networks Biology
Platform: UNKNOWN
Classifier: Development Status :: 4 - Beta
Classifier: Environment :: Console
Classifier: Intended Audience :: Developers
Classifier: Intended Audience :: Science/Research
Classifier: License :: OSI Approved :: Apache Software License
Classifier: Operating System :: OS Independent
Classifier: Programming Language :: Python
Classifier: Programming Language :: Python :: 3.7
Classifier: Programming Language :: Python :: 3.6
Classifier: Programming Language :: Python :: 3 :: Only
Classifier: Topic :: Scientific/Engineering :: Bio-Informatics
Classifier: Topic :: Scientific/Engineering :: Mathematics
Requires-Python: >=3.5
Provides-Extra: docs
